Metadata-Version: 2.1
Name: GB-distributions-class-probability
Version: 0.3
Summary: Gaussian and Binomial distributions
Home-page: UNKNOWN
Author: Raviteja Mangina
Author-email: mangina.raviteja@gmail.com
License: UNKNOWN
Platform: UNKNOWN
